{
  "id": "mountify",
  "timestamp": 1763464987.0,
  "versions": [
    {
      "timestamp": 1764679357.0,
      "version": "v1.8.3",
      "versionCode": 183,
      "zipUrl": "https://yukari0201.github.io/mmrl-repo/modules/mountify/v1.8.3_183.zip",
      "changelog": "https://yukari0201.github.io/mmrl-repo/modules/mountify/v1.8.3_183.md",
      "size": 547010
    },
    {
      "timestamp": 1764727611.0,
      "version": "v1.8.5",
      "versionCode": 185,
      "zipUrl": "https://yukari0201.github.io/mmrl-repo/modules/mountify/v1.8.5_185.zip",
      "changelog": "https://yukari0201.github.io/mmrl-repo/modules/mountify/v1.8.5_185.md",
      "size": 547022
    },
    {
      "timestamp": 1764823526.0,
      "version": "v1.8.6",
      "versionCode": 186,
      "zipUrl": "https://yukari0201.github.io/mmrl-repo/modules/mountify/v1.8.6_186.zip",
      "changelog": "https://yukari0201.github.io/mmrl-repo/modules/mountify/v1.8.6_186.md",
      "size": 547021
    },
    {
      "timestamp": 1766637985.0,
      "version": "v1.8.7",
      "versionCode": 187,
      "zipUrl": "https://yukari0201.github.io/mmrl-repo/modules/mountify/v1.8.7_187.zip",
      "changelog": "https://yukari0201.github.io/mmrl-repo/modules/mountify/v1.8.7_187.md",
      "size": 547019
    },
    {
      "timestamp": 1768130604.0,
      "version": "v1.8.8",
      "versionCode": 188,
      "zipUrl": "https://yukari0201.github.io/mmrl-repo/modules/mountify/v1.8.8_188.zip",
      "changelog": "https://yukari0201.github.io/mmrl-repo/modules/mountify/v1.8.8_188.md",
      "size": 549112
    },
    {
      "timestamp": 1768147805.0,
      "version": "v1.8.9",
      "versionCode": 189,
      "zipUrl": "https://yukari0201.github.io/mmrl-repo/modules/mountify/v1.8.9_189.zip",
      "changelog": "https://yukari0201.github.io/mmrl-repo/modules/mountify/v1.8.9_189.md",
      "size": 548946
    }
  ]
}